firethorn_utils/__init__.py
firethorn_utils/configurator.py
firethorn_utils/parallel.py
firethorn_utils/slack_sender.py
firethorn_utils/system_checker.py
firethorn_utils/tap_validator.py
firethorn_utils/util.py
firethorn_utils/validator.py
firethorn_utils-0.1.0.dist-info/DESCRIPTION.rst
firethorn_utils-0.1.0.dist-info/METADATA
firethorn_utils-0.1.0.dist-info/RECORD
firethorn_utils-0.1.0.dist-info/WHEEL
firethorn_utils-0.1.0.dist-info/metadata.json
firethorn_utils-0.1.0.dist-info/top_level.txt
